{
  "db_name": "SQLite",
  "query": "\n        SELECT id, scopes, expires_at\n        FROM mcp_tokens\n        WHERE token_hash = ?\n        ",
  "describe": {
    "columns": [
      {
        "name": "id",
        "ordinal": 0,
        "type_info": "Integer"
      },
      {
        "name": "scopes",
        "ordinal": 1,
        "type_info": "Text"
      },
      {
        "name": "expires_at",
        "ordinal": 2,
        "type_info": "Text"
      }
    ],
    "parameters": {
      "Right": 1
    },
    "nullable": [
      true,
      true,
      true
    ]
  },
  "hash": "43f6e1d337e189d2c46344ee60f25b30287128f82c42f6e18ba9fea460c24b0e"
}
